NetJin/__init__.py
NetJin/config/__init__.py
NetJin/config/__init__.pyi
NetJin/config/settings.py
NetJin/core/__init__.py
NetJin/core/WebServer/WebServer.py
NetJin/core/WebServer/WebServer.pyi
NetJin/core/WebServer/__init__.py
NetJin/core/base/__init__.py
NetJin/core/base/base.py
NetJin/core/base/base.pyi
NetJin/http/__init__.py
NetJin/http/request.py
NetJin/http/request.pyi
NetJin/http/response.py
NetJin/http/response.pyi
NetJin/types/__init__.py
NetJin/utils/__init__.py
NetJin/utils/extract_route_pattern.py
NetJin/views/errors/NotFound.html
netjin-1.1.1.dist-info/METADATA
netjin-1.1.1.dist-info/WHEEL
netjin-1.1.1.dist-info/RECORD
