Metadata-Version: 2.3
Name: NetJin
Version: 1.1.1
Summary: NetJin is a lightweight web server implemented in Python using sockets. It provides a simple implementation of the HTTP protocol, allowing users to build and run web applications with ease.
Project-URL: Homepage, https://github.com/sachin-acharya-projects/WebServer.py
Project-URL: Issues, https://github.com/sachin-acharya-projects/WebServer.py/issues
Author-email: Sachin Acharya <webserver.py.connect@gmail.com>
Keywords: PythonFramework,WebFramework,Webserver
Classifier: Development Status :: 3 - Alpha
Classifier: License :: OSI Approved :: MIT License
Classifier: Operating System :: OS Independent
Classifier: Programming Language :: Python :: 3
Classifier: Programming Language :: Python :: 3.6
Classifier: Programming Language :: Python :: 3.7
Classifier: Programming Language :: Python :: 3.8
Classifier: Programming Language :: Python :: 3.9
Classifier: Programming Language :: Python :: 3.10
Classifier: Programming Language :: Python :: 3.11
Classifier: Programming Language :: Python :: 3.12
Classifier: Programming Language :: Python :: 3.13
Requires-Python: >=3.10
Requires-Dist: colorama>=0.4.6
Requires-Dist: jinja2>=3.1.4
